LICENSE
README.md
setup.cfg
setup.py
coverxygen/__init__.py
coverxygen/__main__.py
coverxygen.egg-info/PKG-INFO
coverxygen.egg-info/SOURCES.txt
coverxygen.egg-info/dependency_links.txt
coverxygen.egg-info/top_level.txt