Metadata-Version: 2.1
Name: coverxygen
Version: 1.8.1
Summary: Generate doxygen's documentation coverage report
Home-page: https://github.com/psycofdj/coverxygen
Author: Xavier MARCELET
Author-email: xavier@marcelet.com
License: UNKNOWN
Download-URL: https://github.com/psycofdj/coverxygen/tarball/1.8.1
Keywords: doxygen,coverage,python
Platform: UNKNOWN
Classifier: Development Status :: 5 - Production/Stable
Classifier: Environment :: Console
Classifier: Intended Audience :: Developers
Classifier: License :: OSI Approved :: GNU General Public License v3 (GPLv3)
Classifier: Operating System :: Unix
Classifier: Programming Language :: Python :: 3
License-File: LICENSE
